road_rl/__init__.py
road_rl-0.0.1.dist-info/licenses/LICENSE
road_rl-0.0.1.dist-info/METADATA
road_rl-0.0.1.dist-info/WHEEL
road_rl-0.0.1.dist-info/top_level.txt
road_rl-0.0.1.dist-info/RECORD
