Metadata-Version: 2.4
Name: road-rl
Version: 0.0.1
Summary: RoAd-RL - Robust Adversarial Reinforcement Learning
Author: Adithya Mohan
Requires-Python: >=3.8
License-File: LICENSE
Dynamic: license-file
